ttta
