Metadata-Version: 2.4
Name: ttta
Version: 0.9.9
Summary: Tools for temporal text analysis: A Python package providing diachronic tools for text analysis.
Author-email: Kai-Robin Lange <kalange@statistik.tu-dortmund.de>, Lars Grönberg <lars.groenberg@tu-dortmund.de>, Niklas Benner <niklas.benner@rwi-essen.de>, Imene Kolli <imene.kolli@df.uzh.ch>, Aymane Hachcham <aymane.hachcham@df.uzh.ch>, Jonas Rieger <rieger@statistik.tu-dortmund.de>, Carsten Jentsch <jentsch@statistik.tu-dortmund.de>
Keywords: python,nlp,diachronic embeddings,dynamic topic modelling,document scaling
Classifier: Development Status :: 4 - Beta
Classifier: Intended Audience :: End Users/Desktop
Classifier: Intended Audience :: Developers
Classifier: License :: OSI Approved :: GNU General Public License v3 (GPLv3)
Classifier: Programming Language :: Python :: 3
Classifier: Programming Language :: Python :: Implementation :: CPython
Classifier: Operating System :: Unix
Classifier: Operating System :: MacOS :: MacOS X
Classifier: Operating System :: Microsoft :: Windows
License-File: LICENSE
Requires-Dist: nltk
Requires-Dist: Cython
Requires-Dist: pandas
Requires-Dist: scipy
Requires-Dist: numpy
Requires-Dist: tqdm
Requires-Dist: scikit-learn
Requires-Dist: HanTa
Requires-Dist: pyLDAvis>=3.4.0
Requires-Dist: matplotlib
Requires-Dist: seaborn
Provides-Extra: wordcloud
Requires-Dist: wordcloud; extra == "wordcloud"
Provides-Extra: embeddings
Requires-Dist: transformers>=4.46.3; extra == "embeddings"
Requires-Dist: gensim>=4.0.0; extra == "embeddings"
Requires-Dist: torch; extra == "embeddings"
Requires-Dist: wasabi; extra == "embeddings"
Provides-Extra: all
Requires-Dist: transformers>=4.46.3; extra == "all"
Requires-Dist: gensim>=4.0.0; extra == "all"
Requires-Dist: torch; extra == "all"
Requires-Dist: wasabi; extra == "all"
Requires-Dist: wordcloud; extra == "all"
Dynamic: license-file
